dextr/__init__.py
dextr/lr_schedules.py
dextr/model.py
dextr/repeat_sampler.py
dextr/architectures/__init__.py
dextr/architectures/deeplab.py
dextr/architectures/denseunet.py
dextr/architectures/resunet.py
dextr/data_pipeline/__init__.py
dextr/data_pipeline/affine.py
dextr/data_pipeline/dextr_dataset.py
dextr/data_pipeline/dextr_transforms.py
dextr/data_pipeline/pascal_voc_dataset.py
dextr-0.1.2.dist-info/LICENSE
dextr-0.1.2.dist-info/METADATA
dextr-0.1.2.dist-info/WHEEL
dextr-0.1.2.dist-info/top_level.txt
dextr-0.1.2.dist-info/RECORD
