Metadata-Version: 2.1
Name: dextr
Version: 0.1.2
Summary: PyTorch Deep Extreme Cut library
Home-page: https://github.com/Britefury/dextr
Author: Geoff French
License: MIT
Platform: UNKNOWN
Classifier: Development Status :: 3 - Alpha
Classifier: Intended Audience :: Developers
Classifier: Intended Audience :: Science/Research
Classifier: License :: OSI Approved :: MIT License
Classifier: Programming Language :: Python :: 3.7
Classifier: Topic :: Scientific/Engineering :: Artificial Intelligence
Requires-Dist: numpy
Requires-Dist: scipy
Requires-Dist: Pillow
Requires-Dist: scikit-image
Requires-Dist: torch
Requires-Dist: torchvision
Provides-Extra: testing
